submodules/hdl/ip/BITSTREAM_TX.vhd
library ieee;
use ieee.std_logic_1164.all;
use ieee.numeric_std.all;

entity BITSTREAM_TX is
port(
    clk: in std_logic;       --clock 32MHz 
    rst: in std_logic;       --reset
    data_out: out std_logic; --bitstream out
    clk_out : out std_logic  --clock out
);
end entity;

architecture behave of BITSTREAM_TX is 

signal lfsr : unsigned(12 downto 0);
signal i : integer range 0 to 12;

begin
    process(clk,rst)
    begin
        if(rst='1')then 
            lfsr <= "1010001010110";
            data_out <= '0';
            i <= 12;
        elsif(rising_edge(clk))then
            if(i=0)then 
                i <= 12;
                lfsr <= shift_right(lfsr,1);
                lfsr(12) <= lfsr(1) XOR lfsr (0);
                data_out <= lfsr(i);
            else
                i <= i-1;
                data_out <= lfsr(i);
            end if;
        end if;
    end process;

    clk_out <= clk;
end architecture;

submodules/hdl/tb/BITSTREAM_TX_tb.vhd
library ieee;
use ieee.std_logic_1164.all;
use ieee.numeric_std.all;

entity bitstream_tx_tb is
end entity;

architecture behave of bitstream_tx_tb is

component BITSTREAM_TX is
port(
    clk: in std_logic;       --clock 32MHz 
    rst: in std_logic;       --reset
    data_out: out std_logic; --bitstream out
    clk_out : out std_logic  --clock out
);
end component;

signal reset: std_logic;
signal clock: std_logic;
signal datao: std_logic;
signal clock_out:std_logic;

begin
    UUT: BITSTREAM_TX
    port map(clock,reset,datao,clock_out);

    CLK: process
    begin
        clock <= '0';
        wait for 31.25 ns;
        clock <= '1';
        wait for 31.25 ns;
    end process;

    CLC: process
    begin
        reset <= '1';
        wait for 5 ns;
        reset <= '0';
        wait for 5 ns;
        wait for 3100.25 ns;
    end process;
end architecture;

submodules/hdl/vcd/BITSTREAM_TX.vcd
$date
  Sat Jul 02 19:38:41 2022
$end
$version
  GHDL v0
$end
$timescale
  1 fs
$end
$scope module standard $end
$upscope $end
$scope module std_logic_1164 $end
$upscope $end
$scope module numeric_std $end
$upscope $end
$scope module bitstream_tx_tb $end
$var reg 1 ! reset $end
$var reg 1 " clock $end
$var reg 1 # datao $end
$var reg 1 $ clock_out $end
$scope module uut $end
$var reg 1 % clk $end
$var reg 1 & rst $end
$var reg 1 ' data_out $end
$var reg 1 ( clk_out $end
$var reg 13 ) lfsr[12:0] $end
$var integer 32 * i $end
$upscope $end
$upscope $end
$enddefinitions $end
#0
1!
0"
0#
0$
0%
1&
0'
0(
b1010001010110 )
b1100 *
#5000000
0!
0&
#10000000
#31250000
1"
1#
1$
1%
1'
1(
b1011 *
#62500000
0"
0$
0%
0(
#93750000
1"
0#
1$
1%
0'
1(
b1010 *
#125000000
0"
0$
0%
0(
#156250000
1"
1#
1$
1%
1'
1(
b1001 *
#187500000
0"
0$
0%
0(
#218750000
1"
0#
1$
1%
0'
1(
b1000 *
#250000000
0"
0$
0%
0(
#281250000
1"
1$
1%
1(
b111 *
#312500000
0"
0$
0%
0(
#343750000
1"
1$
1%
1(
b110 *
#375000000
0"
0$
0%
0(
#406250000
1"
1#
1$
1%
1'
1(
b101 *
#437500000
0"
0$
0%
0(
#468750000
1"
0#
1$
1%
0'
1(
b100 *
#500000000
0"
0$
0%
0(
#531250000
1"
1#
1$
1%
1'
1(
b11 *
#562500000
0"
0$
0%
0(
#593750000
1"
0#
1$
1%
0'
1(
b10 *
#625000000
0"
0$
0%
0(
#656250000
1"
1#
1$
1%
1'
1(
b1 *
#687500000
0"
0$
0%
0(
#718750000
1"
1$
1%
1(
b0 *
#750000000
0"
0$
0%
0(
#781250000
1"
1$
1%
1(
b1101000101011 )
b1100 *
#812500000
0"
0$
0%
0(
#843750000
1"
1$
1%
1(
b1011 *
#875000000
0"
0$
0%
0(
#906250000
1"
1$
1%
1(
b1010 *
#937500000
0"
0$
0%
0(
#968750000
1"
0#
1$
1%
0'
1(
b1001 *
#1000000000
0"
0$
0%
0(
#1031250000
1"
1#
1$
1%
1'
1(
b1000 *
#1062500000
0"
0$
0%
0(
#1093750000
1"
0#
1$
1%
0'
1(
b111 *
#1125000000
0"
0$
0%
0(
#1156250000
1"
1$
1%
1(
b110 *
#1187500000
0"
0$
0%
0(
#1218750000
1"
1$
1%
1(
b101 *
#1250000000
0"
0$
0%
0(
#1281250000
1"
1#
1$
1%
1'
1(
b100 *
#1312500000
0"
0$
0%
0(
#1343750000
1"
0#
1$
1%
0'
1(
b11 *
#1375000000
0"
0$
0%
0(
#1406250000
1"
1#
1$
1%
1'
1(
b10 *
#1437500000
0"
0$
0%
0(
#1468750000
1"
0#
1$
1%
0'
1(
b1 *
#1500000000
0"
0$
0%
0(
#1531250000
1"
1#
1$
1%
1'
1(
b0 *
#1562500000
0"
0$
0%
0(
#1593750000
1"
1$
1%
1(
b0110100010101 )
b1100 *
#1625000000
0"
0$
0%
0(
#1656250000
1"
0#
1$
1%
0'
1(
b1011 *
#1687500000
0"
0$
0%
0(
#1718750000
1"
1#
1$
1%
1'
1(
b1010 *
#1750000000
0"
0$
0%
0(
#1781250000
1"
1$
1%
1(
b1001 *
#1812500000
0"
0$
0%
0(
#1843750000
1"
0#
1$
1%
0'
1(
b1000 *
#1875000000
0"
0$
0%
0(
#1906250000
1"
1#
1$
1%
1'
1(
b111 *
#1937500000
0"
0$
0%
0(
#1968750000
1"
0#
1$
1%
0'
1(
b110 *
#2000000000
0"
0$
0%
0(
#2031250000
1"
1$
1%
1(
b101 *
#2062500000
0"
0$
0%
0(
#2093750000
1"
1$
1%
1(
b100 *
#2125000000
0"
0$
0%
0(
#2156250000
1"
1#
1$
1%
1'
1(
b11 *
#2187500000
0"
0$
0%
0(
#2218750000
1"
0#
1$
1%
0'
1(
b10 *
#2250000000
0"
0$
0%
0(
#2281250000
1"
1#
1$
1%
1'
1(
b1 *
#2312500000
0"
0$
0%
0(
#2343750000
1"
0#
1$
1%
0'
1(
b0 *
#2375000000
0"
0$
0%
0(
#2406250000
1"
1$
1%
1(
b1011010001010 )
b1100 *
#2437500000
0"
0$
0%
0(
#2468750000
1"
1#
1$
1%
1'
1(
b1011 *
#2500000000
0"
0$
0%
0(
#2531250000
1"
0#
1$
1%
0'
1(
b1010 *
#2562500000
0"
0$
0%
0(
#2593750000
1"
1#
1$
1%
1'
1(
b1001 *
#2625000000
0"
0$
0%
0(
#2656250000
1"
1$
1%
1(
b1000 *
#2687500000
0"
0$
0%
0(
#2718750000
1"
0#
1$
1%
0'
1(
b111 *
#2750000000
0"
0$
0%
0(
#2781250000
1"
1#
1$
1%
1'
1(
b110 *
#2812500000
0"
0$
0%
0(
#2843750000
1"
0#
1$
1%
0'
1(
b101 *
#2875000000
0"
0$
0%
0(
#2906250000
1"
1$
1%
1(
b100 *
#2937500000
0"
0$
0%
0(
#2968750000
1"
1$
1%
1(
b11 *
#3000000000
0"
0$
0%
0(
#3031250000
1"
1#
1$
1%
1'
1(
b10 *
#3062500000
0"
0$
0%
0(
#3093750000
1"
0#
1$
1%
0'
1(
b1 *
