submodules/hdl/ip/BITSTREAM_RX.vhd
library ieee;
use ieee.std_logic_1164.all;
use ieee.numeric_std.all;

entity BITSTREAM_RX is
port(
    clk: in std_logic;
    rst: in std_logic;
    data_in: in std_logic;
    data_out: out unsigned(12 downto 0)
);
end entity;

architecture behave of BITSTREAM_RX is

signal sr : unsigned(12 downto 0);
signal cnt: integer range 0 to 12;

begin
    process(clk,rst)
    begin
        if(rst='1')then
            cnt <= 12;
            sr  <= "0000000000000";
        elsif(falling_edge(clk))then
            if(cnt=0)then
                cnt <= 12;
                data_out <= sr;
                data_out(0) <= data_in; --peut etre pas propre
                sr  <= "0000000000000";
            else
                cnt <= cnt - 1;
                sr(cnt) <= data_in;
            end if;
        end if;
    end process;
end architecture;

submodules/hdl/ip/BITSTREAM_TX.vhd
library ieee;
use ieee.std_logic_1164.all;
use ieee.numeric_std.all;

entity BITSTREAM_TX is
port(
    clk: in std_logic;       --clock 32MHz 
    rst: in std_logic;       --reset
    data_out: out std_logic; --bitstream out
    clk_out : out std_logic  --clock out
);
end entity;

architecture behave of BITSTREAM_TX is 

signal lfsr : unsigned(12 downto 0);
signal i : integer range 0 to 12;

begin
    process(clk,rst)
    begin
        if(rst='1')then 
            lfsr <= "1010001010110";
            data_out <= '0';
            i <= 12;
        elsif(rising_edge(clk))then
            if(i=0)then 
                i <= 12;
                lfsr <= shift_right(lfsr,1);
                lfsr(12) <= lfsr(1) XOR lfsr (0);
                data_out <= lfsr(i);
            else
                i <= i-1;
                data_out <= lfsr(i);
            end if;
        end if;
    end process;

    clk_out <= clk;
end architecture;

submodules/hdl/tb/BITSTREAM_RX_tb.vhd
library ieee;
use ieee.std_logic_1164.all;
use ieee.numeric_std.all;

entity bitstream_rx_tb is
end entity;

architecture behave of bitstream_rx_tb is

component BITSTREAM_TX is
port(
    clk: in std_logic;       --clock 32MHz 
    rst: in std_logic;       --reset
    data_out: out std_logic; --bitstream out
    clk_out : out std_logic  --clock out
);
end component;
component BITSTREAM_RX is
port(
    clk: in std_logic;
    rst: in std_logic;
    data_in: in std_logic;
    data_out: out unsigned(12 downto 0)
);
end component;

signal sim_reset : std_logic;
signal sim_clock : std_logic;
signal io        : std_logic;
signal clk_io    : std_logic;
signal data_out  : unsigned(12 downto 0);


begin
    UUT0: BITSTREAM_TX
    port map(sim_clock,sim_reset,io,clk_io);
    UUT1: BITSTREAM_RX
    port map(clk_io,sim_reset,io,data_out);

    CLK: process
    begin
        sim_clock <= '0';
        wait for 31.25 ns;
        sim_clock <= '1';
        wait for 31.25 ns;
    end process;

    CLC: process
    begin
        sim_reset <= '1';
        wait for 5 ns;
        sim_reset <= '0';
        wait for 5 ns;
        wait for 3100.25 ns;
    end process;
end architecture;

submodules/hdl/vcd/BITSTREAM_RX.vcd
$date
  Sat Jul 02 20:04:29 2022
$end
$version
  GHDL v0
$end
$timescale
  1 fs
$end
$scope module standard $end
$upscope $end
$scope module std_logic_1164 $end
$upscope $end
$scope module numeric_std $end
$upscope $end
$scope module bitstream_rx_tb $end
$var reg 1 ! sim_reset $end
$var reg 1 " sim_clock $end
$var reg 1 # io $end
$var reg 1 $ clk_io $end
$var reg 13 % data_out[12:0] $end
$scope module uut0 $end
$var reg 1 & clk $end
$var reg 1 ' rst $end
$var reg 1 ( data_out $end
$var reg 1 ) clk_out $end
$var reg 13 * lfsr[12:0] $end
$var integer 32 + i $end
$upscope $end
$scope module uut1 $end
$var reg 1 , clk $end
$var reg 1 - rst $end
$var reg 1 . data_in $end
$var reg 13 / data_out[12:0] $end
$var reg 13 0 sr[12:0] $end
$var integer 32 1 cnt $end
$upscope $end
$upscope $end
$enddefinitions $end
#0
1!
0"
0#
0$
bUUUUUUUUUUUUU %
0&
1'
0(
0)
b1010001010110 *
b1100 +
0,
1-
0.
bUUUUUUUUUUUUU /
b0000000000000 0
b1100 1
#5000000
0!
0'
0-
#10000000
#31250000
1"
1#
1$
1&
1(
1)
b1011 +
1,
1.
#62500000
0"
0$
0&
0)
0,
b1000000000000 0
b1011 1
#93750000
1"
0#
1$
1&
0(
1)
b1010 +
1,
0.
#125000000
0"
0$
0&
0)
0,
b1010 1
#156250000
1"
1#
1$
1&
1(
1)
b1001 +
1,
1.
#187500000
0"
0$
0&
0)
0,
b1010000000000 0
b1001 1
#218750000
1"
0#
1$
1&
0(
1)
b1000 +
1,
0.
#250000000
0"
0$
0&
0)
0,
b1000 1
#281250000
1"
1$
1&
1)
b111 +
1,
#312500000
0"
0$
0&
0)
0,
b111 1
#343750000
1"
1$
1&
1)
b110 +
1,
#375000000
0"
0$
0&
0)
0,
b110 1
#406250000
1"
1#
1$
1&
1(
1)
b101 +
1,
1.
#437500000
0"
0$
0&
0)
0,
b1010001000000 0
b101 1
#468750000
1"
0#
1$
1&
0(
1)
b100 +
1,
0.
#500000000
0"
0$
0&
0)
0,
b100 1
#531250000
1"
1#
1$
1&
1(
1)
b11 +
1,
1.
#562500000
0"
0$
0&
0)
0,
b1010001010000 0
b11 1
#593750000
1"
0#
1$
1&
0(
1)
b10 +
1,
0.
#625000000
0"
0$
0&
0)
0,
b10 1
#656250000
1"
1#
1$
1&
1(
1)
b1 +
1,
1.
#687500000
0"
0$
0&
0)
0,
b1010001010100 0
b1 1
#718750000
1"
1$
1&
1)
b0 +
1,
#750000000
0"
0$
0&
0)
0,
b1010001010110 0
b0 1
#781250000
1"
0#
1$
1&
0(
1)
b1101000101011 *
b1100 +
1,
0.
#812500000
0"
0$
b1010001010110 %
0&
0)
0,
b1010001010110 /
b0000000000000 0
b1100 1
#843750000
1"
1#
1$
1&
1(
1)
b1011 +
1,
1.
#875000000
0"
0$
0&
0)
0,
b1000000000000 0
b1011 1
#906250000
1"
1$
1&
1)
b1010 +
1,
#937500000
0"
0$
0&
0)
0,
b1100000000000 0
b1010 1
#968750000
1"
0#
1$
1&
0(
1)
b1001 +
1,
0.
#1000000000
0"
0$
0&
0)
0,
b1001 1
#1031250000
1"
1#
1$
1&
1(
1)
b1000 +
1,
1.
#1062500000
0"
0$
0&
0)
0,
b1101000000000 0
b1000 1
#1093750000
1"
0#
1$
1&
0(
1)
b111 +
1,
0.
#1125000000
0"
0$
0&
0)
0,
b111 1
#1156250000
1"
1$
1&
1)
b110 +
1,
#1187500000
0"
0$
0&
0)
0,
b110 1
#1218750000
1"
1$
1&
1)
b101 +
1,
#1250000000
0"
0$
0&
0)
0,
b101 1
#1281250000
1"
1#
1$
1&
1(
1)
b100 +
1,
1.
#1312500000
0"
0$
0&
0)
0,
b1101000100000 0
b100 1
#1343750000
1"
0#
1$
1&
0(
1)
b11 +
1,
0.
#1375000000
0"
0$
0&
0)
0,
b11 1
#1406250000
1"
1#
1$
1&
1(
1)
b10 +
1,
1.
#1437500000
0"
0$
0&
0)
0,
b1101000101000 0
b10 1
#1468750000
1"
0#
1$
1&
0(
1)
b1 +
1,
0.
#1500000000
0"
0$
0&
0)
0,
b1 1
#1531250000
1"
1#
1$
1&
1(
1)
b0 +
1,
1.
#1562500000
0"
0$
0&
0)
0,
b1101000101010 0
b0 1
#1593750000
1"
1$
1&
1)
b0110100010101 *
b1100 +
1,
#1625000000
0"
0$
b1101000101011 %
0&
0)
0,
b1101000101011 /
b0000000000000 0
b1100 1
#1656250000
1"
0#
1$
1&
0(
1)
b1011 +
1,
0.
#1687500000
0"
0$
0&
0)
0,
b1011 1
#1718750000
1"
1#
1$
1&
1(
1)
b1010 +
1,
1.
#1750000000
0"
0$
0&
0)
0,
b0100000000000 0
b1010 1
#1781250000
1"
1$
1&
1)
b1001 +
1,
#1812500000
0"
0$
0&
0)
0,
b0110000000000 0
b1001 1
#1843750000
1"
0#
1$
1&
0(
1)
b1000 +
1,
0.
#1875000000
0"
0$
0&
0)
0,
b1000 1
#1906250000
1"
1#
1$
1&
1(
1)
b111 +
1,
1.
#1937500000
0"
0$
0&
0)
0,
b0110100000000 0
b111 1
#1968750000
1"
0#
1$
1&
0(
1)
b110 +
1,
0.
#2000000000
0"
0$
0&
0)
0,
b110 1
#2031250000
1"
1$
1&
1)
b101 +
1,
#2062500000
0"
0$
0&
0)
0,
b101 1
#2093750000
1"
1$
1&
1)
b100 +
1,
#2125000000
0"
0$
0&
0)
0,
b100 1
#2156250000
1"
1#
1$
1&
1(
1)
b11 +
1,
1.
#2187500000
0"
0$
0&
0)
0,
b0110100010000 0
b11 1
#2218750000
1"
0#
1$
1&
0(
1)
b10 +
1,
0.
#2250000000
0"
0$
0&
0)
0,
b10 1
#2281250000
1"
1#
1$
1&
1(
1)
b1 +
1,
1.
#2312500000
0"
0$
0&
0)
0,
b0110100010100 0
b1 1
#2343750000
1"
0#
1$
1&
0(
1)
b0 +
1,
0.
#2375000000
0"
0$
0&
0)
0,
b0 1
#2406250000
1"
1#
1$
1&
1(
1)
b1011010001010 *
b1100 +
1,
1.
#2437500000
0"
0$
b0110100010101 %
0&
0)
0,
b0110100010101 /
b0000000000000 0
b1100 1
#2468750000
1"
1$
1&
1)
b1011 +
1,
#2500000000
0"
0$
0&
0)
0,
b1000000000000 0
b1011 1
#2531250000
1"
0#
1$
1&
0(
1)
b1010 +
1,
0.
#2562500000
0"
0$
0&
0)
0,
b1010 1
#2593750000
1"
1#
1$
1&
1(
1)
b1001 +
1,
1.
#2625000000
0"
0$
0&
0)
0,
b1010000000000 0
b1001 1
#2656250000
1"
1$
1&
1)
b1000 +
1,
#2687500000
0"
0$
0&
0)
0,
b1011000000000 0
b1000 1
#2718750000
1"
0#
1$
1&
0(
1)
b111 +
1,
0.
#2750000000
0"
0$
0&
0)
0,
b111 1
#2781250000
1"
1#
1$
1&
1(
1)
b110 +
1,
1.
#2812500000
0"
0$
0&
0)
0,
b1011010000000 0
b110 1
#2843750000
1"
0#
1$
1&
0(
1)
b101 +
1,
0.
#2875000000
0"
0$
0&
0)
0,
b101 1
#2906250000
1"
1$
1&
1)
b100 +
1,
#2937500000
0"
0$
0&
0)
0,
b100 1
#2968750000
1"
1$
1&
1)
b11 +
1,
#3000000000
0"
0$
0&
0)
0,
b11 1
#3031250000
1"
1#
1$
1&
1(
1)
b10 +
1,
1.
#3062500000
0"
0$
0&
0)
0,
b1011010001000 0
b10 1
#3093750000
1"
0#
1$
1&
0(
1)
b1 +
1,
0.
