submodules/hdl/ip/ETH_10BASE-T.vhd
library ieee;
use ieee.std_logic_1164.all;
use ieee.numeric_std.all;

entity ETH_10BASE_T is
port(
    --input
    rst: in std_logic;
    clk: in std_logic;
    snd: in std_logic;
    --ethernet RD differential pair
    rdp: out std_logic;
    rdm: out std_logic;
    --ethernet TD differential pair
    tdp: out std_logic;
    tdm: out std_logic
);
end entity;

architecture behave of ETH_10BASE_T is
-- finite state machine 
type t_state is (IDLE,SENDING);
signal state : t_state;
-- ethernet layer 
signal ethPreamb : unsigned(63 downto 0);
signal ethDstAdd : unsigned(47 downto 0);
signal ethSrcAdd : unsigned(47 downto 0);
signal ethType   : unsigned(15 downto 0);
-- ip layer 
signal ipHeader  : unsigned(71 downto 0);
signal ipProtocol: unsigned( 7 downto 0);
signal ipChkSum  : unsigned(15 downto 0);
signal ipSrc     : unsigned(31 downto 0);
signal ipDst     : unsigned(31 downto 0);
-- udp layer
signal udpSrcPort: unsigned(15 downto 0);
signal udpDstPort: unsigned(15 downto 0);
signal udpPldLen : unsigned(15 downto 0);
signal udpChkSum : unsigned(15 downto 0);
signal udpPayload: unsigned(143 downto 0);
-- ethernet layer
signal ethChkSum : unsigned(31 downto 0);
--
signal ethFrame  : unsigned(575 downto 0);
signal i : integer range 0 to 575;
signal tds : std_logic;

begin
    process(clk,rst)
    begin
        if(rst='1')then
            state     <= IDLE;
            i         <= 0;
            ethPreamb <= X"55_55_55_55_55_55_55_D5";
            ethDstAdd <= X"00_10_A4_7B_EA_80";
            ethSrcAdd <= X"00_12_34_56_78_90";
            ethType   <= X"08_00";
            ipHeader  <= X"45_00_00_2E_B3_FE_00_00_80";
            ipProtocol<= X"11";
            ipChkSum  <= X"05_40";
            ipSrc     <= X"C0_A8_00_2C";
            ipDst     <= X"C0_A8_00_04";
            udpSrcPort<= X"04_00";
            udpDstPort<= X"04_00";
            udpPldLen <= X"00_1A";
            udpChkSum <= X"2D_E8";
            udpPayload<= X"00_01_02_03_04_05_06_07_08_09_0A_0B_0C_0D_0E_0F_10_11";
            ethChkSUm <= X"B3_31_88_1B";
        elsif(clk'event AND clk='1')then
            case state is
                when IDLE =>
                    if(snd='1')then
                        state <= SENDING;
                    else
                        tdp <= 'X';
                        tdm <= 'X';
                        tds <= 'X';
                        i <= 0; 
                        state <= IDLE;
                    end if;
                when SENDING =>
                    if(i/=63)then
                        if(ethPreamb(i)='0')then
                            tdp <= '1';
                            tdm <= '0';
                            tds <= '0';
                        elsif(ethPreamb(i)='1')then
                            tdp <= '0';
                            tdm <= '1';
                            tds <= '1';
                        else
                            i <= 0;  
                            state <= IDLE;
                        end if;
                        i <= i+1;
                    else
                        i <= 0;
                        state <= IDLE;
                    end if;
            end case;
        elsif(clk'event AND clk='0')then
            case state is
                when IDLE => -- do nothing
                when SENDING =>
                    if(tds='0')then
                        tdp <= '0';
                        tdm <= '1';
                    elsif(tds='1')then
                        tdp <= '1';
                        tdm <= '0';
                    end if;
            end case;
        end if;
    end process;
end architecture;

submodules/hdl/tb/ETH_10BASE-T_tb.vhd
library ieee;
use ieee.std_logic_1164.all;
use ieee.numeric_std.all;

entity eth_10baset_tb is 
end entity;

architecture behave of eth_10baset_tb is

component ETH_10BASE_T is
    port(
        --input
        rst: in std_logic;
        clk: in std_logic;
        snd: in std_logic;
        --ethernet RD differential pair
        rdp: out std_logic;
        rdm: out std_logic;
        --ethernet TD differential pair
        tdp: out std_logic;
        tdm: out std_logic
    );
end component;

signal reset: std_logic;
signal clock: std_logic;
signal send : std_logic;
signal TD_POSITIVE : std_logic;
signal TD_NEGATIVE : std_logic;
signal RD_POSITIVE : std_logic;
signal RD_NEGATIVE : std_logic;

begin 
    UUT: ETH_10BASE_T
    port map(reset,clock,send,RD_POSITIVE,RD_NEGATIVE,TD_POSITIVE,TD_NEGATIVE);

    CLK: process
    begin
        clock <= '0';
        wait for 10 ns;
        clock <= '1';
        wait for 10 ns;
    end process;

    CLC: process
    begin
        reset <= '1';
        send <= '0';
        wait for 10 ns;
        reset <= '0';
        send <= '1';
        wait for 10 ns;
        send <= '0';
        wait for 3100 ns;
    end process;

end architecture;

submodules/hdl/vcd/eth_10baset_tb.vcd
$date
  Sun Jul 03 19:05:27 2022
$end
$version
  GHDL v0
$end
$timescale
  1 fs
$end
$scope module standard $end
$upscope $end
$scope module std_logic_1164 $end
$upscope $end
$scope module numeric_std $end
$upscope $end
$scope module eth_10baset_tb $end
$var reg 1 ! reset $end
$var reg 1 " clock $end
$var reg 1 # send $end
$var reg 1 $ td_positive $end
$var reg 1 % td_negative $end
$var reg 1 & rd_positive $end
$var reg 1 ' rd_negative $end
$scope module uut $end
$var reg 1 ( rst $end
$var reg 1 ) clk $end
$var reg 1 * snd $end
$var reg 1 + rdp $end
$var reg 1 , rdm $end
$var reg 1 - tdp $end
$var reg 1 . tdm $end
$comment state is not handled $end
$var reg 64 / ethpreamb[63:0] $end
$var reg 48 0 ethdstadd[47:0] $end
$var reg 48 1 ethsrcadd[47:0] $end
$var reg 16 2 ethtype[15:0] $end
$var reg 72 3 ipheader[71:0] $end
$var reg 8 4 ipprotocol[7:0] $end
$var reg 16 5 ipchksum[15:0] $end
$var reg 32 6 ipsrc[31:0] $end
$var reg 32 7 ipdst[31:0] $end
$var reg 16 8 udpsrcport[15:0] $end
$var reg 16 9 udpdstport[15:0] $end
$var reg 16 : udppldlen[15:0] $end
$var reg 16 ; udpchksum[15:0] $end
$var reg 144 < udppayload[143:0] $end
$var reg 32 = ethchksum[31:0] $end
$var reg 576 > ethframe[575:0] $end
$var integer 32 ? i $end
$var reg 1 @ tds $end
$upscope $end
$upscope $end
$enddefinitions $end
#0
1!
0"
0#
U$
U%
U&
U'
1(
0)
0*
U+
U,
U-
U.
b0101010101010101010101010101010101010101010101010101010111010101 /
b000000000001000010100100011110111110101010000000 0
b000000000001001000110100010101100111100010010000 1
b0000100000000000 2
b010001010000000000000000001011101011001111111110000000000000000010000000 3
b00010001 4
b0000010101000000 5
b11000000101010000000000000101100 6
b11000000101010000000000000000100 7
b0000010000000000 8
b0000010000000000 9
b0000000000011010 :
b0010110111101000 ;
b000000000000000100000010000000110000010000000101000001100000011100001000000010010000101000001011000011000000110100001110000011110001000000010001 <
b10110011001100011000100000011011 =
bUUUUUUUUUUUUUUUUUUUUUUUUUUUUUUUUUUUUUUUUUUUUUUUUUUUUUUUUUUUUUUUUUUUUUUUUUUUUUUUUUUUUUUUUUUUUUUUUUUUUUUUUUUUUUUUUUUUUUUUUUUUUUUUUUUUUUUUUUUUUUUUUUUUUUUUUUUUUUUUUUUUUUUUUUUUUUUUUUUUUUUUUUUUUUUUUUUUUUUUUUUUUUUUUUUUUUUUUUUUUUUUUUUUUUUUUUUUUUUUUUUUUUUUUUUUUUUUUUUUUUUUUUUUUUUUUUUUUUUUUUUUUUUUUUUUUUUUUUUUUUUUUUUUUUUUUUUUUUUUUUUUUUUUUUUUUUUUUUUUUUUUUUUUUUUUUUUUUUUUUUUUUUUUUUUUUUUUUUUUUUUUUUUUUUUUUUUUUUUUUUUUUUUUUUUUUUUUUUUUUUUUUUUUUUUUUUUUUUUUUUUUUUUUUUUUUUUUUUUUUUUUUUUUUUUUUUUUUUUUUUUUUUUUUUUUUUUUUUUUUUUUUUUUUUUUUUUUUUUUUUUUUUUUUUUUUUUUUUUUUUUUUUUUUUUUUUUUUUUUUUUUUUUUUUUUUUUUU >
b0 ?
U@
#10000000
0!
1"
1#
0(
1)
1*
#20000000
0"
0#
0)
0*
#30000000
1"
0$
1%
1)
0-
1.
b1 ?
1@
#40000000
0"
1$
0%
0)
1-
0.
#50000000
1"
1)
b10 ?
0@
#60000000
0"
0$
1%
0)
0-
1.
#70000000
1"
1)
b11 ?
1@
#80000000
0"
1$
0%
0)
1-
0.
#90000000
1"
1)
b100 ?
0@
#100000000
0"
0$
1%
0)
0-
1.
#110000000
1"
1)
b101 ?
1@
#120000000
0"
1$
0%
0)
1-
0.
#130000000
1"
1)
b110 ?
0@
#140000000
0"
0$
1%
0)
0-
1.
#150000000
1"
1)
b111 ?
1@
#160000000
0"
1$
0%
0)
1-
0.
#170000000
1"
0$
1%
1)
0-
1.
b1000 ?
#180000000
0"
1$
0%
0)
1-
0.
#190000000
1"
0$
1%
1)
0-
1.
b1001 ?
#200000000
0"
1$
0%
0)
1-
0.
#210000000
1"
1)
b1010 ?
0@
#220000000
0"
0$
1%
0)
0-
1.
#230000000
1"
1)
b1011 ?
1@
#240000000
0"
1$
0%
0)
1-
0.
#250000000
1"
1)
b1100 ?
0@
#260000000
0"
0$
1%
0)
0-
1.
#270000000
1"
1)
b1101 ?
1@
#280000000
0"
1$
0%
0)
1-
0.
#290000000
1"
1)
b1110 ?
0@
#300000000
0"
0$
1%
0)
0-
1.
#310000000
1"
1)
b1111 ?
1@
#320000000
0"
1$
0%
0)
1-
0.
#330000000
1"
1)
b10000 ?
0@
#340000000
0"
0$
1%
0)
0-
1.
#350000000
1"
1)
b10001 ?
1@
#360000000
0"
1$
0%
0)
1-
0.
#370000000
1"
1)
b10010 ?
0@
#380000000
0"
0$
1%
0)
0-
1.
#390000000
1"
1)
b10011 ?
1@
#400000000
0"
1$
0%
0)
1-
0.
#410000000
1"
1)
b10100 ?
0@
#420000000
0"
0$
1%
0)
0-
1.
#430000000
1"
1)
b10101 ?
1@
#440000000
0"
1$
0%
0)
1-
0.
#450000000
1"
1)
b10110 ?
0@
#460000000
0"
0$
1%
0)
0-
1.
#470000000
1"
1)
b10111 ?
1@
#480000000
0"
1$
0%
0)
1-
0.
#490000000
1"
1)
b11000 ?
0@
#500000000
0"
0$
1%
0)
0-
1.
#510000000
1"
1)
b11001 ?
1@
#520000000
0"
1$
0%
0)
1-
0.
#530000000
1"
1)
b11010 ?
0@
#540000000
0"
0$
1%
0)
0-
1.
#550000000
1"
1)
b11011 ?
1@
#560000000
0"
1$
0%
0)
1-
0.
#570000000
1"
1)
b11100 ?
0@
#580000000
0"
0$
1%
0)
0-
1.
#590000000
1"
1)
b11101 ?
1@
#600000000
0"
1$
0%
0)
1-
0.
#610000000
1"
1)
b11110 ?
0@
#620000000
0"
0$
1%
0)
0-
1.
#630000000
1"
1)
b11111 ?
1@
#640000000
0"
1$
0%
0)
1-
0.
#650000000
1"
1)
b100000 ?
0@
#660000000
0"
0$
1%
0)
0-
1.
#670000000
1"
1)
b100001 ?
1@
#680000000
0"
1$
0%
0)
1-
0.
#690000000
1"
1)
b100010 ?
0@
#700000000
0"
0$
1%
0)
0-
1.
#710000000
1"
1)
b100011 ?
1@
#720000000
0"
1$
0%
0)
1-
0.
#730000000
1"
1)
b100100 ?
0@
#740000000
0"
0$
1%
0)
0-
1.
#750000000
1"
1)
b100101 ?
1@
#760000000
0"
1$
0%
0)
1-
0.
#770000000
1"
1)
b100110 ?
0@
#780000000
0"
0$
1%
0)
0-
1.
#790000000
1"
1)
b100111 ?
1@
#800000000
0"
1$
0%
0)
1-
0.
#810000000
1"
1)
b101000 ?
0@
#820000000
0"
0$
1%
0)
0-
1.
#830000000
1"
1)
b101001 ?
1@
#840000000
0"
1$
0%
0)
1-
0.
#850000000
1"
1)
b101010 ?
0@
#860000000
0"
0$
1%
0)
0-
1.
#870000000
1"
1)
b101011 ?
1@
#880000000
0"
1$
0%
0)
1-
0.
#890000000
1"
1)
b101100 ?
0@
#900000000
0"
0$
1%
0)
0-
1.
#910000000
1"
1)
b101101 ?
1@
#920000000
0"
1$
0%
0)
1-
0.
#930000000
1"
1)
b101110 ?
0@
#940000000
0"
0$
1%
0)
0-
1.
#950000000
1"
1)
b101111 ?
1@
#960000000
0"
1$
0%
0)
1-
0.
#970000000
1"
1)
b110000 ?
0@
#980000000
0"
0$
1%
0)
0-
1.
#990000000
1"
1)
b110001 ?
1@
#1000000000
0"
1$
0%
0)
1-
0.
#1010000000
1"
1)
b110010 ?
0@
#1020000000
0"
0$
1%
0)
0-
1.
#1030000000
1"
1)
b110011 ?
1@
#1040000000
0"
1$
0%
0)
1-
0.
#1050000000
1"
1)
b110100 ?
0@
#1060000000
0"
0$
1%
0)
0-
1.
#1070000000
1"
1)
b110101 ?
1@
#1080000000
0"
1$
0%
0)
1-
0.
#1090000000
1"
1)
b110110 ?
0@
#1100000000
0"
0$
1%
0)
0-
1.
#1110000000
1"
1)
b110111 ?
1@
#1120000000
0"
1$
0%
0)
1-
0.
#1130000000
1"
1)
b111000 ?
0@
#1140000000
0"
0$
1%
0)
0-
1.
#1150000000
1"
1)
b111001 ?
1@
#1160000000
0"
1$
0%
0)
1-
0.
#1170000000
1"
1)
b111010 ?
0@
#1180000000
0"
0$
1%
0)
0-
1.
#1190000000
1"
1)
b111011 ?
1@
#1200000000
0"
1$
0%
0)
1-
0.
#1210000000
1"
1)
b111100 ?
0@
#1220000000
0"
0$
1%
0)
0-
1.
#1230000000
1"
1)
b111101 ?
1@
#1240000000
0"
1$
0%
0)
1-
0.
#1250000000
1"
1)
b111110 ?
0@
#1260000000
0"
0$
1%
0)
0-
1.
#1270000000
1"
1)
b111111 ?
1@
#1280000000
0"
1$
0%
0)
1-
0.
#1290000000
1"
1)
b0 ?
#1300000000
0"
0)
#1310000000
1"
X$
X%
1)
X-
X.
X@
